tkinter_videoplayer/__init__.py
tkinter_videoplayer/controls.py
tkinter_videoplayer/events.py
tkinter_videoplayer/player.py
tkinter_videoplayer/theme.py
tkinter_videoplayer/video.py
tkinter_videoplayer/media/pause.png
tkinter_videoplayer/media/play.png
tkinter_videoplayer-1.3.1.dist-info/licenses/LICENSE
tkinter_videoplayer-1.3.1.dist-info/METADATA
tkinter_videoplayer-1.3.1.dist-info/WHEEL
tkinter_videoplayer-1.3.1.dist-info/top_level.txt
tkinter_videoplayer-1.3.1.dist-info/RECORD
