Metadata-Version: 2.4
Name: tkinter-videoplayer
Version: 1.3.1
Summary: A simple video player widget for Tkinter.
Author-email: cmdr2 <dev@cmdr2.org>
License: MIT License
Project-URL: Homepage, https://github.com/cmdr2/tkinter-videoplayer
Project-URL: Repository, https://github.com/cmdr2/tkinter-videoplayer
Requires-Python: >=3.7
License-File: LICENSE
Requires-Dist: opencv-python
Requires-Dist: Pillow
Dynamic: license-file
